patrom.py
patrom-0.0.1.dist-info/DESCRIPTION.rst
patrom-0.0.1.dist-info/METADATA
patrom-0.0.1.dist-info/RECORD
patrom-0.0.1.dist-info/WHEEL
patrom-0.0.1.dist-info/metadata.json
patrom-0.0.1.dist-info/top_level.txt
