Metadata-Version: 2.0
Name: patrom
Version: 0.0.1
Summary: patrom is a Python web templating engine
Home-page: https://github.com/PierreQuentel/patrom
Author: Pierre Quentel
Author-email: quentel.pierre@orange.fr
License: BSD
Keywords: Python web template
Platform: UNKNOWN
Classifier: Intended Audience :: Developers
Classifier: Topic :: Software Development :: Interpreters
Classifier: Operating System :: OS Independent
Classifier: License :: OSI Approved :: BSD License
Classifier: Programming Language :: Python :: 3
